odoo/addons/account_move_force_removal/README.rst
odoo/addons/account_move_force_removal/__init__.py
odoo/addons/account_move_force_removal/__manifest__.py
odoo/addons/account_move_force_removal/i18n/account_move_force_removal.pot
odoo/addons/account_move_force_removal/models/__init__.py
odoo/addons/account_move_force_removal/models/account_move.py
odoo/addons/account_move_force_removal/readme/CONTRIBUTORS.rst
odoo/addons/account_move_force_removal/readme/DESCRIPTION.rst
odoo/addons/account_move_force_removal/readme/USAGE.rst
odoo/addons/account_move_force_removal/static/description/icon.png
odoo/addons/account_move_force_removal/static/description/index.html
odoo/addons/account_move_force_removal/tests/__init__.py
odoo/addons/account_move_force_removal/tests/test_move.py
odoo14_addon_account_move_force_removal-14.0.1.0.1.dist-info/METADATA
odoo14_addon_account_move_force_removal-14.0.1.0.1.dist-info/WHEEL
odoo14_addon_account_move_force_removal-14.0.1.0.1.dist-info/top_level.txt
odoo14_addon_account_move_force_removal-14.0.1.0.1.dist-info/RECORD
